Workbook

Sheet Inputs
A1: Jordans Profile
A3: Annual Income | B3: 62000
A4: Monthly Income | B4: =B3/12 -> 5166.6667
A5: Current Savings | B5: 8000
A6: 401k Contribution Rate | B6: 0.06
A7: Employer Match | B7: 0.5
A8: Monthly Commute Miles | B8: 800
A9: Analysis Period (Years) | B9: 5
A10: Analysis Period (Months) | B10: =B9*12 -> 60
A12: Buy Assumptions
A14: Buy Upfront Cost | B14: 4000
A15: Buy Monthly Loan Payment | B15: 480
A16: Loan Term Months | B16: 60
A17: Buy Monthly Insurance | B17: 140
A18: Buy Monthly Gas | B18: 120
A19: Buy Annual Maintenance | B19: 500
A20: Buy Resale Value Year 5 | B20: 13000
A22: Lease Assumptions
A24: Lease Upfront Cost | B24: 2500
A25: Lease Monthly Payment | B25: 390
A26: Lease Term Months | B26: 36
A27: Lease Monthly Insurance | B27: 150
A28: Lease Monthly Gas | B28: 120
A29: Lease Annual Maintenance | B29: 200
A31: Hybrid Assumptions
A33: Transit | B33: 24 | C33: months
A34: Lease | B34: 36 | C34: months
A36: Transit/Rideshare assumptions
A38: Transit Monthly Cost | B38: 380
A39: Low Fluctuation Rate | B39: -0.1
A40: High Fluctuation Rate | B40: 0.1
A42: Shared Assumptions
A44: Insurance Growth Rate | B44: 0.03
A45: Discount / Investment Rate (optional TVM) | B45: 0.05

Sheet Buy_Model
A1: Year | B1: 1 | C1: 2 | D1: 3 | E1: 4 | F1: 5
A2: Upfront Cost | B2: =Inputs!B14 -> 4000 | C2: =0 -> 0 | D2: =0 -> 0 | E2: =0 -> 0 | F2: =0 -> 0
A3: Loan Payments | B3: =Inputs!B15*12 -> 5760 | C3: =Inputs!B15*12 -> 5760 | D3: =Inputs!B15*12 -> 5760 | E3: =Inputs!B15*12 -> 5760 | F3: =Inputs!B15*12 -> 5760
A4: Insurance | B4: =Inputs!B17*12 -> 1680 | C4: =B4*(1+Inputs!B44) -> 1730.4 | D4: =C4*(1+Inputs!B44) -> 1782.312 | E4: =D4*(1+Inputs!B44) -> 1835.7814 | F4: =E4*(1+Inputs!B44) -> 1890.8548
A5: Gas | B5: =Inputs!B18*12 -> 1440 | C5: =Inputs!B18*12 -> 1440 | D5: =Inputs!B18*12 -> 1440 | E5: =Inputs!B18*12 -> 1440 | F5: =Inputs!B18*12 -> 1440
A6: Maintenance | B6: =Inputs!B19 -> 500 | C6: =Inputs!B19 -> 500 | D6: =Inputs!B19 -> 500 | E6: =Inputs!B19 -> 500 | F6: =Inputs!B19 -> 500
A7: Gross Annual Cost | B7: =SUM(B2:B6) -> 13380 | C7: =SUM(C2:C6) -> 9430.4 | D7: =SUM(D2:D6) -> 9482.312 | E7: =SUM(E2:E6) -> 9535.7814 | F7: =SUM(F2:F6) -> 9590.8548
A8: Resale Value | B8: =0 -> 0 | C8: =0 -> 0 | D8: =0 -> 0 | E8: =0 -> 0 | F8: =Inputs!B20 -> 13000
A9: Net Annual Cost | B9: =B7-B8 -> 13380 | C9: =C7-C8 -> 9430.4 | D9: =D7-D8 -> 9482.312 | E9: =E7-E8 -> 9535.7814 | F9: =F7-F8 -> -3409.1452
A11: Total 5 year Buy Cost | B11: =SUM(B9:F9) -> 38419.348
A13: TMV Analysis | Discount Rate 5%
A14: Discount Factor 5% | B14: =1/(1+Inputs!B45)^1 -> 0.95238095 | C14: =1/(1+Inputs!B45)^2 -> 0.90702948 | D14: =1/(1+Inputs!B45)^3 -> 0.8638376 | E14: =1/(1+Inputs!B45)^4 -> 0.82270247 | F14: =1/(1+Inputs!B45)^5 -> 0.78352617
A15: PV of Annual Cost | B15: =B9*B14 -> 12742.857 | C15: =C9*C14 -> 8553.6508 | D15: =D9*D14 -> 8191.1776 | E15: =E9*E14 -> 7845.1109 | F15: =F9*F14 -> -2671.1545
A16: Discounted 5 Year Buy Cost | B16: =SUM(B15:F15) -> 34661.642

Sheet Hybrid_Model
B2: Phase 1 | C2: Phase 1 | D2: Phase 2 | E2: Phase 2 | F2: Phase 2
A3: Year | B3: 1 | C3: 2 | D3: 3 | E3: 4 | F3: 5
A4: Upfront Cost | B4: 0 | C4: 0 | D4: =Inputs!B24 -> 2500 | E4: =0 -> 0 | F4: =0 -> 0
A5: Monthly Payments | B5: =Inputs!B38*12 -> 4560 | C5: =Inputs!B38*12 -> 4560 | D5: =Inputs!B25*12 -> 4680 | E5: =Inputs!B25*12 -> 4680 | F5: =Inputs!B25*12 -> 4680
A6: Insurance | B6: 0 | C6: =B6*(1+Inputs!B44) -> 0 | D6: =Inputs!B27*12 -> 1800 | E6: =D6*(1+Inputs!B44) -> 1854 | F6: =E6*(1+Inputs!B44) -> 1909.62
A7: Gas | B7: 0 | C7: 0 | D7: =Inputs!B28*12 -> 1440 | E7: =Inputs!B28*12 -> 1440 | F7: =Inputs!B28*12 -> 1440
A8: Maintenance | B8: 0 | C8: 0 | D8: =Inputs!B29 -> 200 | E8: =Inputs!B29 -> 200 | F8: =Inputs!B29 -> 200
A9: Gross Annual Cost | B9: =SUM(B4:B8) -> 4560 | C9: =SUM(C4:C8) -> 4560 | D9: =SUM(D4:D8) -> 10620 | E9: =SUM(E4:E8) -> 8174 | F9: =SUM(F4:F8) -> 8229.62
A10: Resale Value | B10: 0 | C10: 0 | D10: 0 | E10: 0 | F10: 0
A11: Net Annual Cost | B11: =B9-B10 -> 4560 | C11: =C9-C10 -> 4560 | D11: =D9-D10 -> 10620 | E11: =E9-E10 -> 8174 | F11: =F9-F10 -> 8229.62
A13: Total 5 year Hybrid Cost | B13: =SUM(B11:F11) -> 36143.62
A15: TMV Analysis | Discount Rate 5%
A16: Discount Factor 5% | B16: =1/(1+Inputs!B45)^1 -> 0.95238095 | C16: =1/(1+Inputs!B45)^2 -> 0.90702948 | D16: =1/(1+Inputs!B45)^3 -> 0.8638376 | E16: =1/(1+Inputs!B45)^4 -> 0.82270247 | F16: =1/(1+Inputs!B45)^5 -> 0.78352617
A17: PV of Annual Cost | B17: =B11*B16 -> 4342.8571 | C17: =C11*C16 -> 4136.0544 | D17: =D11*D16 -> 9173.9553 | E17: =E11*E16 -> 6724.77 | F17: =F11*F16 -> 6448.1226
A18: Discounted 5 Year Hybrid Cost | B18: =SUM(B17:F17) -> 30825.76

Sheet Transit_Model
A1: Year | B1: 1 | C1: 2 | D1: 3 | E1: 4 | F1: 5
A2: Monthly Cost | B2: =Inputs!B38 -> 380 | C2: =Inputs!B38 -> 380 | D2: =Inputs!B38 -> 380 | E2: =Inputs!B38 -> 380 | F2: =Inputs!B38 -> 380
A3: Annual Transit Cost | B3: =B2*12 -> 4560 | C3: =B2*12 -> 4560 | D3: =B2*12 -> 4560 | E3: =B2*12 -> 4560 | F3: =B2*12 -> 4560
A4: Net Annual Cost | B4: =B3 -> 4560 | C4: =C3 -> 4560 | D4: =D3 -> 4560 | E4: =E3 -> 4560 | F4: =F3 -> 4560
A6: Total 5 Year Transit/Rideshare Cost | B6: =SUM(B4:F4) -> 22800
A8: TMV Analysis | Discount Rate 5%
A9: Discount Factor 5% | B9: =1/(1+Inputs!$B$45)^1 -> 0.95238095 | C9: =1/(1+Inputs!$B$45)^2 -> 0.90702948 | D9: =1/(1+Inputs!$B$45)^3 -> 0.8638376 | E9: =1/(1+Inputs!$B$45)^4 -> 0.82270247 | F9: =1/(1+Inputs!$B$45)^5 -> 0.78352617
A10: PV of Annual Cost | B10: =B4*B9 -> 4342.8571 | C10: =C4*C9 -> 4136.0544 | D10: =D4*D9 -> 3939.0994 | E10: =E4*E9 -> 3751.5233 | F10: =F4*F9 -> 3572.8793
A11: Discounted 5 Year Transit Cost | B11: =SUM(B10:F10) -> 19742.414

Sheet Comparsion
A1: KPI (Key Perfomance Indicators)
A2: Buy 5-Year Cost | B2: =Buy_Model!B11 -> 38419.348
A3: Hybrid 5-Year Cost | B3: =Hybrid_Model!B13 -> 36143.62
A4: Transit 5-Year Cost | B4: =Transit_Model!B6 -> 22800
A7: Savings of Hybrid vs Buy | B7: =B2-B3 -> 2275.7282
A8: Savings of Transit vs Buy | B8: =B2-B4 -> 15619.348
A9: Savings of Transit vs Hybrid | B9: =B3-B4 -> 13343.62
A12: Buy Monthly Burden | B12: =Inputs!B15+Inputs!B17+Inputs!B18+(Inputs!B19/12) -> 781.66667
A13: Hybrid Monthly Burden | B13: =B3/60 -> 602.39367 | C13: (blended avg across both phases)
A14: Transit Monthly Burden | B14: =Inputs!B38 -> 380
A17: Hybrid Savings vs Buy (monthly) | B17: =B12-B13 -> 179.273
A18: Transit Savings vs Hybrid (monthly) | B18: =B13-B14 -> 222.39367
A19: Transit Savings vs Buy (monthly) | B19: =B12-B14 -> 401.66667
A21: Decision Matrix
A23: Criteria | B23: Buy | C23: Transit | D23: Hybrid
A24: Cost | B24: 3 | C24: 5 | D24: 4
A25: Liquidity | B25: 2 | C25: 5 | D25: 4
A26: Flexibility | B26: 5 | C26: 3 | D26: 4
A27: Sustainability | B27: 4 | C27: 5 | D27: 4
A28: Home Goal Alignment | B28: 2 | C28: 5 | D28: 4
A29: Total Score | B29: 16 | C29: 23 | D29: 20
A31: We used a 1-to-5 decision matrix, where 1 represents the weakest performance and 5 represents the strongest performance. This helped us compare each option not only on total financial cost, but also on liquidity, flexibility, sustainability, and how well it supports Jordan’s goal of buying a home in five years.
A33: TVM
A34: Buy 5 Year Cost | B34: =Buy_Model!B16 -> 34661.642 | C34: upfront $4k + loan int makes early cost heavier
A35: Hybrid 5 Year Cost | B35: =Hybrid_Model!B18 -> 30825.76 | C35: Back loaded lease costs discounted more
A36: Transit | B36: =Transit_Model!B11 -> 19742.414 | C36: Flat costs discounted evenly across all 5 years

Sheet Sensitivity
A1: Hybrid Strategy Sensitivity Analysis
A3: Quantitative Risk: Transit Cost Fluctuation 10%
A4: Scenario | B4: Transit Rate | C4: Phase 1 Cost (Years 1-2) | D4: Phase 2 Cost (Fixed) | E4: Hybrid Total | F4: vs Base Case
A5: Low Case (-10%) | B5: -0.1 | C5: =Inputs!B38*(1+Inputs!B39)*24 -> 8208 | D5: =Inputs!B24+Inputs!B25*12*3+Inputs!B27*12*(1+(1+Inputs!B44)+(1+Inputs!B44)^2)+Inputs!B28*12*3+Inputs!B29*3 -> 27023.62 | E5: =C5+D5 -> 35231.62 | F5: =E5-E6 -> -912
A6: Base Case (0%) | B6: 0 | C6: =Inputs!B38*24 -> 9120 | D6: =Inputs!B24+Inputs!B25*12*3+Inputs!B27*12*(1+(1+Inputs!B44)+(1+Inputs!B44)^2)+Inputs!B28*12*3+Inputs!B29*3 -> 27023.62 | E6: =C6+D6 -> 36143.62
A7: High Case (+10%) | B7: 0.1 | C7: =Inputs!B38*(1+Inputs!B40)*24 -> 10032 | D7: =Inputs!B24+Inputs!B25*12*3+Inputs!B27*12*(1+(1+Inputs!B44)+(1+Inputs!B44)^2)+Inputs!B28*12*3+Inputs!B29*3 -> 27023.62 | E7: =C7+D7 -> 37055.62 | F7: =E7-E6 -> 912
A9: Insight: Phase 2 lease costs are fixed by contract, only 24 month transit phase carries cost uncertainty
A12: Qualitative Risk: Transit Service Availability
A13: Risk Factor | B13: Likelihood | C13: Financial Impact | D13: Jordan's Exposure | E13: Mitigation | F13: Hybrid Advantage
A14: Transit Disruption ( strikes, service cuts) | B14: Low-Medium | C14: Rideshare costs spike during Phase 1 | D14: Months 1-24 only; Phase 2 lease eliminates this risk | E14: Keep $1000-$2000 emergency buffer from early savings | F14: Lease provides own vehicle by Year 3
A15: Rideshare price surge (demand spikes) | B15: Medium (10% tested above) | C15: Up to +$912 over 24 months at worst | D15: Bounded; worst case still $1,253 cheaper than Buy | E15: Use public transit as primary; rideshare as supplement only | F15: Fixed lease costs give certainty from Year 3 onward
A17: Insight: Transit risk is real but time limited to Phase 1 only. The lease eliminates service availability risk entirely from Year 3
A19: Risk Summary
A20: Transit Cost Spread (Low to High) | B20: =E7-E5 -> 1824 | C20: Only $1824 between worst and best transit scenario
A21: Lease phase cost (Phase 2) | B21: =Inputs!B24+Inputs!B25*12*3+Inputs!B27*12*(1+(1+Inputs!B44)+(1+Inputs!B44)^2)+Inputs!B28*12*3+Inputs!B29*3 -> 27023.62 | C21: Contractually fixed, zero fluctuation risk in Years 3-5
A22: Hybrid worst case vs Buy | B22: =E7-Buy_Model!B11 -> -1363.7282 | C22: Hybrid still cheaper than Buy even in worst case
